check_techstack_vulnerabilities/TechStack.py
check_techstack_vulnerabilities/__init__.py
check_techstack_vulnerabilities/__main__.py
check_techstack_vulnerabilities-1.0.2.dist-info/LICENSE
check_techstack_vulnerabilities-1.0.2.dist-info/METADATA
check_techstack_vulnerabilities-1.0.2.dist-info/WHEEL
check_techstack_vulnerabilities-1.0.2.dist-info/top_level.txt
check_techstack_vulnerabilities-1.0.2.dist-info/RECORD
