Metadata-Version: 2.1
Name: check-techstack-vulnerabilities
Version: 1.0.2
Summary: UNKNOWN
Home-page: https://github.com/devarajug/check-techstack-vulnerabilities
Author: Devaraju Garigapati
Author-email: devarajugarigapati@gmail.com
License: MIT
Platform: UNKNOWN
Classifier: Programming Language :: Python :: 3
Classifier: License :: OSI Approved :: MIT License
Classifier: Operating System :: OS Independent
Requires-Python: >=3.6
License-File: LICENSE
Requires-Dist: pandas
Requires-Dist: openpyxl
Requires-Dist: lxml
Requires-Dist: requests
Requires-Dist: beautifulsoup4
